vital-model-chars2vec-onnx/__init__.py
vital-model-chars2vec-onnx/chars2vec_onnx.py
vital_model_chars2vec_onnx/__init__.py
vital_model_chars2vec_onnx/chars2vec_onnx.py
vital_model_chars2vec_onnx/models/en_300/model.onnx
vital_model_chars2vec_onnx/models/en_300/model.pkl
vital_model_chars2vec_onnx-0.1.0.dist-info/METADATA
vital_model_chars2vec_onnx-0.1.0.dist-info/WHEEL
vital_model_chars2vec_onnx-0.1.0.dist-info/top_level.txt
vital_model_chars2vec_onnx-0.1.0.dist-info/RECORD
